spark_connectby/__init__.py
spark_connectby/connectby_query.py
spark_connectby/query.py
spark_connectby-1.0.4.dist-info/METADATA
spark_connectby-1.0.4.dist-info/WHEEL
spark_connectby-1.0.4.dist-info/RECORD
